<?xml version="1.0" encoding="utf-8" ?>
<Defs>
  <InteractionDef>
    <defName>Thought</defName>
    <label>thought</label>
    <symbol>Things/Mote/SpeechSymbols/Gears</symbol>
    <logRulesInitiator>
      <rulesStrings>
        <li>r_logentry(hasOtherPawn==false)->[INITIATOR_nameDef] thought about [INITIATOR_possessive] [thought_label].</li>
        <li>r_logentry(hasOtherPawn==false)->[INITIATOR_nameDef] thought to themselves about [INITIATOR_possessive] [thought_label].</li>
        <li>r_logentry(hasOtherPawn==true)->[INITIATOR_nameDef] thought about [INITIATOR_possessive] [thought_label] with [OTHER_PAWN_nameDef].</li>
        <li>r_logentry(hasOtherPawn==true)->[INITIATOR_nameDef] thought to themselves about [INITIATOR_possessive] [thought_label] with [OTHER_PAWN_nameDef].</li>
      </rulesStrings>
    </logRulesInitiator>
  </InteractionDef>
 </Defs>
